adxp_cli/__init__.py
adxp_cli/agent/__init__.py
adxp_cli/agent/cli.py
adxp_cli/agent/deployment.py
adxp_cli/agent/docker.py
adxp_cli/agent/port.py
adxp_cli/agent/run.py
adxp_cli/agent/validation.py
adxp_cli/apikey/README.md
adxp_cli/apikey/cli.py
adxp_cli/apikey/service.py
adxp_cli/auth/__init__.py
adxp_cli/auth/cli.py
adxp_cli/auth/schema.py
adxp_cli/auth/service.py
adxp_cli/authorization/README.md
adxp_cli/authorization/__init__.py
adxp_cli/authorization/cli.py
adxp_cli/authorization/groups.py
adxp_cli/authorization/projects.py
adxp_cli/authorization/users.py
adxp_cli/authorization/utils.py
adxp_cli/cli.py
adxp_cli/common/__init__.py
adxp_cli/common/exec.py
adxp_cli/common/progress.py
adxp_cli/common/utils.py
adxp_cli/dataset/__init__.py
adxp_cli/dataset/cli.py
adxp_cli/finetuning/__init__.py
adxp_cli/finetuning/cli.py
adxp_cli/finetuning/metrics.py
adxp_cli/finetuning/trainer.py
adxp_cli/finetuning/training.py
adxp_cli/finetuning/utils.py
adxp_cli/knowledge/cli.py
adxp_cli/lineage/__init__.py
adxp_cli/lineage/cli.py
adxp_cli/model/README.md
adxp_cli/model/__init__.py
adxp_cli/model/cli.py
adxp_cli/model/custom_runtime.py
adxp_cli/model/deploy.py
adxp_cli/model/endpoint.py
adxp_cli/model/model.py
adxp_cli/model/provider.py
adxp_cli/model/version.py
adxp_cli/prompts/__init__.py
adxp_cli/prompts/cli.py
adxp_cli/test/dataset/files/benchmark_data.csv
adxp_cli/test/dataset/files/benchmark_data.zip
adxp_cli/test/dataset/files/dpo_data.csv
adxp_cli/test/dataset/files/supervised_data.csv
adxp_cli/test/dataset/files/unsupervised_data.csv
adxp_cli/test/dataset/files/unsupervised_data2.csv
adxp_cli/test/dataset/test_cli_usage.py
adxp_cli/test/finetuning/test_backend_ai_endpoints.py
adxp_cli/test/finetuning/test_cli_usage.py
adxp_cli/test/lineage/test_lineage_usage.py
adxp_cli/test/model/test_cli_models.py
adxp_cli/test/model/test_cli_usage.py
adxp_cli/test/prompts/cli_usage_example.py
adxp_cli-0.1.19.dist-info/METADATA
adxp_cli-0.1.19.dist-info/WHEEL
adxp_cli-0.1.19.dist-info/entry_points.txt
adxp_cli-0.1.19.dist-info/RECORD
