Metadata-Version: 2.4
Name: adxp-cli
Version: 0.1.19
Summary: AIX Platform CLI
License: Proprietary
Author: AIX Enterprise
Requires-Python: >=3.10,<4.0
Classifier: License :: Other/Proprietary License
Classifier: Programming Language :: Python :: 3
Classifier: Programming Language :: Python :: 3.10
Classifier: Programming Language :: Python :: 3.11
Classifier: Programming Language :: Python :: 3.12
Classifier: Programming Language :: Python :: 3.13
Classifier: Programming Language :: Python :: 3.14
Provides-Extra: langchain
Requires-Dist: adxp-sdk (>=0.1.15)
Requires-Dist: langchain (>=0.3.0) ; extra == "langchain"
Requires-Dist: langchain-community (>=0.3.0) ; extra == "langchain"
Requires-Dist: langchain-openai (>=0.2.0) ; extra == "langchain"
Requires-Dist: langgraph (>=0.2.26) ; extra == "langchain"
Requires-Dist: pydantic[email] (<=2.10.6)
Requires-Dist: requests-toolbelt (>=1.0.0,<2.0.0)
Requires-Dist: tabulate (>=0.9.0,<0.10.0)
